etos_test_runner/__init__.py
etos_test_runner/etr.py
etos_test_runner/lib/__init__.py
etos_test_runner/lib/checkout.sh
etos_test_runner/lib/custom_dataset.py
etos_test_runner/lib/decrypt.py
etos_test_runner/lib/environ.sh
etos_test_runner/lib/events.py
etos_test_runner/lib/executor.py
etos_test_runner/lib/executor.sh
etos_test_runner/lib/iut.py
etos_test_runner/lib/iut_monitoring.py
etos_test_runner/lib/log_area.py
etos_test_runner/lib/testrunner.py
etos_test_runner/lib/verdict.py
etos_test_runner/lib/workspace.py
etos_test_runner/plugins/__init__.py
etos_test_runner/plugins/plugin.py
etos_test_runner-3.7.6.dist-info/licenses/AUTHORS.rst
etos_test_runner-3.7.6.dist-info/licenses/LICENSE.txt
etr_send_event/__init__.py
etos_test_runner-3.7.6.dist-info/METADATA
etos_test_runner-3.7.6.dist-info/WHEEL
etos_test_runner-3.7.6.dist-info/top_level.txt
etos_test_runner-3.7.6.dist-info/RECORD
