Metadata-Version: 2.4
Name: etos_test_runner
Version: 3.7.6
Summary: ETOS Test Runner
Author-email: Tobias Persson <tobias.persson@axis.com>
License: Apache License, Version 2.0
Project-URL: Documentation, https://etos.readthedocs.io/
Project-URL: Homepage, https://github.com/eiffel-community/etos-test-runner
Project-URL: Repository, https://github.com/eiffel-community/etos-test-runner
Classifier: Development Status :: 4 - Beta
Classifier: Programming Language :: Python :: 3
Classifier: License :: OSI Approved :: Apache Software License
License-File: LICENSE.txt
License-File: AUTHORS.rst
Requires-Dist: etos_lib==5.1.5
Requires-Dist: cryptography<43.0.0,>=42.0.4
Requires-Dist: packageurl-python==0.9.1
Requires-Dist: jsontas<2.0.0,>=1.4.1
Requires-Dist: opentelemetry-api==1.39.0
Requires-Dist: opentelemetry-sdk==1.39.0
Requires-Dist: opentelemetry-exporter-otlp==1.39.0
Requires-Dist: opentelemetry-semantic-conventions==0.60b0
Requires-Dist: opentelemetry-instrumentation-logging==0.60b0
Provides-Extra: testing
Requires-Dist: pytest; extra == "testing"
Requires-Dist: pytest-cov; extra == "testing"
Dynamic: license-file
